reddit_monitor.py
reddit_market_research-0.3.0.dist-info/METADATA
reddit_market_research-0.3.0.dist-info/WHEEL
reddit_market_research-0.3.0.dist-info/entry_points.txt
reddit_market_research-0.3.0.dist-info/licenses/LICENSE
reddit_market_research-0.3.0.dist-info/RECORD
